__init__.py
mol_patents_find.py
mongo/__init__.py
mongo/mongo_configs.py
mongo/mongo_connector.py
patent_finder/__init__.py
patent_finder/patent_finder_mongo_db.py
utils/__init__.py
utils/common_types.py
utils/common_utils.py
better_moles_patent_finder-0.1.2.dist-info/LICENSE
better_moles_patent_finder-0.1.2.dist-info/METADATA
better_moles_patent_finder-0.1.2.dist-info/WHEEL
better_moles_patent_finder-0.1.2.dist-info/entry_points.txt
better_moles_patent_finder-0.1.2.dist-info/top_level.txt
better_moles_patent_finder-0.1.2.dist-info/RECORD
