Metadata-Version: 2.2
Name: better-moles-patent-finder
Version: 0.1.2
Summary: A tool designed to enhance patent discovery by leveraging MongoDB for efficient storage, querying, and analysis of patent data. This repository includes features to streamline patent searches, improve retrieval accuracy, and support advanced filtering and indexing capabilities.
Author-email: Fabio Bove <fabio.bove.dr@gmail.com>
License:                     GNU GENERAL PUBLIC LICENSE
Project-URL: Homepage, https://github.com/fabiobove-dr/better-moles-patent-finder
Project-URL: Issues, https://github.com/fabiobove-dr/better-moles-patent-finder/issues
Keywords: molecules,bioinformatics,patent-finder,molecules-evaluation,mongo_db
License-File: LICENSE
Requires-Dist: numpy<2.0.0,>=1.0.0
Requires-Dist: pandas==2.2.3
Requires-Dist: pymongo==4.9
Requires-Dist: rdkit==2024.3.6
Requires-Dist: tqdm==4.67.1
Provides-Extra: test
Requires-Dist: pytest==7.2.1; extra == "test"
Requires-Dist: pytest-cov==5.0.0; extra == "test"
Requires-Dist: pytest-mock==3.14.0; extra == "test"
